google/api/field_behavior_pb2.py
google/cloud/alloydb/connector/__init__.py
google/cloud/alloydb_connectors_v1/proto/__init__.py
google/cloud/alloydb_connectors_v1/proto/resources_pb2.py
google/cloud/alloydb_connectors_v1/proto/resources_pb2.pyi
google/cloud/alloydbconnector/__init__.py
google/cloud/alloydbconnector/async_connector.py
google/cloud/alloydbconnector/asyncpg.py
google/cloud/alloydbconnector/client.py
google/cloud/alloydbconnector/connection_info.py
google/cloud/alloydbconnector/connector.py
google/cloud/alloydbconnector/enums.py
google/cloud/alloydbconnector/exceptions.py
google/cloud/alloydbconnector/instance.py
google/cloud/alloydbconnector/lazy.py
google/cloud/alloydbconnector/pg8000.py
google/cloud/alloydbconnector/py.typed
google/cloud/alloydbconnector/rate_limiter.py
google/cloud/alloydbconnector/refresh_utils.py
google/cloud/alloydbconnector/static.py
google/cloud/alloydbconnector/types.py
google/cloud/alloydbconnector/utils.py
google/cloud/alloydbconnector/version.py
google_cloud_alloydb_connector-1.11.0.dist-info/licenses/LICENSE
google_cloud_alloydb_connector-1.11.0.dist-info/METADATA
google_cloud_alloydb_connector-1.11.0.dist-info/WHEEL
google_cloud_alloydb_connector-1.11.0.dist-info/top_level.txt
google_cloud_alloydb_connector-1.11.0.dist-info/RECORD
