Metadata-Version: 2.4
Name: google-cloud-alloydb-connector
Version: 1.11.0
Summary: A Python client library for connecting securely to your Google Cloud AlloyDB instances.
Author-email: Google LLC <googleapis-packages@google.com>
License-Expression: Apache-2.0
Project-URL: Homepage, https://github.com/GoogleCloudPlatform/alloydb-python-connector
Project-URL: Repository, https://github.com/GoogleCloudPlatform/alloydb-python-connector.git
Project-URL: Issues, https://github.com/GoogleCloudPlatform/alloydb-python-connector/issues
Project-URL: Changelog, https://github.com/GoogleCloudPlatform/alloydb-python-connector/blob/main/CHANGELOG.md
Classifier: Development Status :: 5 - Production/Stable
Classifier: Intended Audience :: Developers
Classifier: Programming Language :: Python
Classifier: Programming Language :: Python :: 3
Classifier: Programming Language :: Python :: 3.10
Classifier: Programming Language :: Python :: 3.11
Classifier: Programming Language :: Python :: 3.12
Classifier: Programming Language :: Python :: 3.13
Classifier: Programming Language :: Python :: 3.14
Classifier: Operating System :: OS Independent
Requires-Python: >=3.10
License-File: LICENSE
Requires-Dist: aiofiles
Requires-Dist: cryptography>=42.0.0
Requires-Dist: requests
Requires-Dist: google-auth
Requires-Dist: protobuf
Requires-Dist: google-cloud-alloydb
Requires-Dist: google-api-core
Provides-Extra: pg8000
Requires-Dist: pg8000>=1.31.1; extra == "pg8000"
Provides-Extra: asyncpg
Requires-Dist: asyncpg>=0.31.0; extra == "asyncpg"
Dynamic: license-file
